fancy/descriptor/LICENSE.txt
fancy/descriptor/README.md
fancy/descriptor/__init__.py
fancy/descriptor/method_descriptor_base/__init__.py
fancy/descriptor/method_descriptor_base/method_descriptor.py
fancy/descriptor/method_descriptor_base/method_descriptor_base.py
fancy/descriptor/method_descriptor_base/simple_method_descriptor.py
fancy/descriptor/method_descriptor_factories/__init__.py
fancy/descriptor/method_descriptor_factories/method_descriptor_factories.py
fancy/descriptor/method_descriptor_factories/method_descriptor_factory_base.py
fancy/descriptor/patterns/__init__.py
fancy/descriptor/patterns/singleton.py
fancy/descriptor/tests/__init__.py
fancy/descriptor/tests/unit/__init__.py
fancy/descriptor/tests/unit/method_descriptor_base/__init__.py
fancy/descriptor/tests/unit/method_descriptor_base/fake_descriptor.py
fancy/descriptor/tests/unit/method_descriptor_base/fake_marked.py
fancy/descriptor/tests/unit/method_descriptor_base/test_method_descriptors.py
fancy/descriptor/tests/unit/method_descriptor_factories/__init__.py
fancy/descriptor/tests/unit/method_descriptor_factories/fake_method_descriptor_factory.py
fancy/descriptor/tests/unit/method_descriptor_factories/test_method_descriptor_factories.py
fancy/descriptor/tests/unit/method_descriptor_factories/test_method_descriptor_factory_base.py
fancy_descriptor-1.2.0a2.dist-info/METADATA
fancy_descriptor-1.2.0a2.dist-info/WHEEL
fancy_descriptor-1.2.0a2.dist-info/top_level.txt
fancy_descriptor-1.2.0a2.dist-info/RECORD
