Metadata-Version: 2.1
Name: fancy-descriptor
Version: 1.2.0a2
Summary: This package add a callable descriptor called method descriptor which can apply on methods.
Home-page: UNKNOWN
Author: su-rin
Author-email: susautw@gmail.com
License: UNKNOWN
Project-URL: Source Code, https://github.com/susautw/fancy_descriptors
Keywords: descriptor
Platform: UNKNOWN
Classifier: Programming Language :: Python :: 3
Classifier: License :: OSI Approved :: MIT License
Classifier: Operating System :: OS Independent
Requires-Python: >=3.6
